geom.py
geom-0.3.0.dist-info/LICENSE
geom-0.3.0.dist-info/METADATA
geom-0.3.0.dist-info/WHEEL
geom-0.3.0.dist-info/top_level.txt
geom-0.3.0.dist-info/RECORD
