Metadata-Version: 2.1
Name: geom
Version: 0.3.0
Summary: Useful functions and classes for geometry
Home-page: https://github.com/josiest/geom
Author: Josie Thompson
Author-email: dot.slash.josie@gmail.com
License: MIT
Platform: UNKNOWN
Classifier: Development Status :: 1 - Planning
Classifier: Intended Audience :: Developers
Classifier: License :: OSI Approved :: MIT License
Classifier: Operating System :: POSIX :: Linux
Classifier: Programming Language :: Python :: 3 :: Only
Classifier: Topic :: Utilities
License-File: LICENSE
